mozyq/__init__.py
mozyq/app.py
mozyq/cnst.py
mozyq/frame.py
mozyq/io.py
mozyq/mozyq_types.py
mozyq/mzq.py
mozyq/norm.py
mozyq/transition.py
mozyq/util.py
mozyq-0.0.22.dist-info/METADATA
mozyq-0.0.22.dist-info/WHEEL
mozyq-0.0.22.dist-info/entry_points.txt
mozyq-0.0.22.dist-info/RECORD
