Metadata-Version: 2.4
Name: mozyq
Version: 0.0.22
Project-URL: Homepage, https://mozyq.org
Project-URL: Repository, https://github.com/mozyq/app/
Author-email: Gilad Kutiel <gilad.kutiel@gmail.com>
Requires-Python: <3.13,>=3.10
Requires-Dist: cattrs>=23.2
Requires-Dist: click>=8.3
Requires-Dist: ffmpeg-python>=0.2.0
Requires-Dist: opencv-python>=4.10
Requires-Dist: pillow>=10.0.0
Requires-Dist: psutil>=7.1.0
Requires-Dist: scikit-image>=0.25.2
Requires-Dist: scipy>=1.14
Requires-Dist: tqdm>=4.66.5
Requires-Dist: typer>=0.19
